LICENSE
yubrary/yu_requests.py
yubrary-1.0.0.dist-info/LICENSE
yubrary-1.0.0.dist-info/WHEEL
yubrary-1.0.0.dist-info/METADATA
yubrary-1.0.0.dist-info/RECORD
